bookmark_tk-0.7.2.dist-info/licenses/LICENSE
btk/__init__.py
btk/archiver.py
btk/auto_tag.py
btk/browser_import.py
btk/cli.py
btk/config.py
btk/constants.py
btk/content_cache.py
btk/content_extractor.py
btk/content_fetcher.py
btk/db.py
btk/dedup.py
btk/exporters.py
btk/graph.py
btk/importers.py
btk/models.py
btk/plugins.py
btk/progress.py
btk/shell.py
btk/tag_utils.py
btk/utils.py
bookmark_tk-0.7.2.dist-info/METADATA
bookmark_tk-0.7.2.dist-info/WHEEL
bookmark_tk-0.7.2.dist-info/entry_points.txt
bookmark_tk-0.7.2.dist-info/top_level.txt
bookmark_tk-0.7.2.dist-info/RECORD
