Metadata-Version: 2.4
Name: bookmark-tk
Version: 0.7.2
Summary: Bookmark Toolkit. Helps manage, analyze, and visualize bookmarks
Author-email: Alex Towell <lex@metafunctor.com>
Requires-Python: >=3.8
License-File: LICENSE
Requires-Dist: bs4
Requires-Dist: requests
Requires-Dist: colorama
Requires-Dist: rich
Requires-Dist: networkx
Requires-Dist: matplotlib
Requires-Dist: pyvis
Requires-Dist: tqdm
Requires-Dist: jmespath
Dynamic: license-file
